__init__.py
setup.py
South.egg-info/PKG-INFO
South.egg-info/SOURCES.txt
South.egg-info/dependency_links.txt
South.egg-info/top_level.txt
docs/CHANGELOG
docs/CONTRIBUTING
docs/LICENSE
docs/README
south/__init__.py
south/migration.py
south/models.py
south/modelsparser.py
south/orm.py
south/db/__init__.py
south/db/generic.py
south/db/mysql.py
south/db/postgresql_psycopg2.py
south/db/sqlite3.py
south/db/sql_server/__init__.py
south/db/sql_server/pyodbc.py
south/management/__init__.py
south/management/commands/__init__.py
south/management/commands/migrate.py
south/management/commands/startmigration.py
south/management/commands/syncdb.py
south/management/commands/test.py
south/tests/__init__.py
south/tests/db.py
south/tests/logic.py
south/tests/modelsparser.py
south/tests/fakeapp/__init__.py
south/tests/fakeapp/models.py
south/tests/fakeapp/migrations/0001_spam.py
south/tests/fakeapp/migrations/0002_eggs.py
south/tests/fakeapp/migrations/0003_alter_spam.py
south/tests/fakeapp/migrations/__init__.py