Metadata-Version: 1.0
Name: South
Version: 0.5
Summary: South: Migrations for Django
Home-page: http://south.aeracode.org/
Author: Andrew Godwin & Andy McCurdy
Author-email: south@aeracode.org
License: UNKNOWN
Download-URL: http://south.aeracode.org/wiki/Download
Platform: UNKNOWN
Classifier: Development Status :: 5 - Production/Stable
Classifier: Framework :: Django
Classifier: Intended Audience :: Developers
Classifier: Intended Audience :: System Administrators
Classifier: Intended Audience :: System Administrators
Classifier: License :: OSI Approved :: Apache Software License
Classifier: Operating System :: OS Independent
Classifier: Topic :: Software Development
